dcc/__init__.py
dcc/__main__.py
dcc/ply/__init__.py
dcc/ply/cpp.py
dcc/ply/ctokens.py
dcc/ply/lex.py
dcc/ply/yacc.py
dcc/ply/ygen.py
dccompiler-0.0.3.dist-info/METADATA
dccompiler-0.0.3.dist-info/WHEEL
dccompiler-0.0.3.dist-info/top_level.txt
dccompiler-0.0.3.dist-info/RECORD
